{
  "kind": "collectionType",
  "collectionName": "books",
  "info": {
    "singularName": "book",
    "pluralName": "books",
    "displayName": "Book",
    "description": ""
  },
  "options": {
    "draftAndPublish": false
  },
  "pluginOptions": {},
  "attributes": {
    "title": {
      "type": "string",
      "required": true,
      "maxLength": 50
    },
    "pages": {
      "type": "integer",
      "required": false,
      "min": 1
    },
    "cover": {
      "type": "media",
      "multiple": false,
      "required": false,
      "allowedTypes": ["images"]
    },
    "year": {
      "type": "integer"
    },
    "authors": {
      "type": "relation",
      "relation": "manyToMany",
      "target": "api::author.author",
      "inversedBy": "books"
    }
  }
}
